{
    "objs": [
        {
            "id": 1406,
            "pos": [
                {
                    "pos": {
                        "x": 40.70000076293945,
                        "y": 109.46800231933594,
                        "z": 32.5
                    },
                    "rot": 252.08700561523438
                },
                {
                    "pos": {
                        "x": 30.936180114746095,
                        "y": 84.08769989013672,
                        "z": 24.819442749023439
                    },
                    "rot": 19.835872650146486
                },
                {
                    "pos": {
                        "x": 29.92255401611328,
                        "y": 84.09443664550781,
                        "z": 37.49125671386719
                    },
                    "rot": 29.39141082763672
                },
                {
                    "pos": {
                        "x": 17.239723205566408,
                        "y": 84.09523010253906,
                        "z": 24.83355712890625
                    },
                    "rot": 35.04216384887695
                },
                {
                    "pos": {
                        "x": 29.98894500732422,
                        "y": 84.09390258789063,
                        "z": 13.932754516601563
                    },
                    "rot": 16.82793426513672
                },
                {
                    "pos": {
                        "x": 42.40009307861328,
                        "y": 84.09347534179688,
                        "z": 24.54747772216797
                    },
                    "rot": 4.309959888458252
                }
            ]
        }
    ],
    "paths": [],
    "areas": []
}