{
    "objs": [
        {
            "id": 1412,
            "pos": [
                {
                    "pos": {
                        "x": 36.57814025878906,
                        "y": 23.25391960144043,
                        "z": 122.07470703125
                    },
                    "rot": 199.7989959716797
                },
                {
                    "pos": {
                        "x": 41.0669059753418,
                        "y": 23.25391960144043,
                        "z": 122.04682922363281
                    },
                    "rot": 254.69076538085938
                },
                {
                    "pos": {
                        "x": 39.059505462646487,
                        "y": 23.25391960144043,
                        "z": 119.23089599609375
                    },
                    "rot": 295.9189453125
                },
                {
                    "pos": {
                        "x": 37.8388671875,
                        "y": 23.25391960144043,
                        "z": 159.47410583496095
                    },
                    "rot": 227.04534912109376
                },
                {
                    "pos": {
                        "x": 35.60651779174805,
                        "y": 23.25391960144043,
                        "z": 157.68270874023438
                    },
                    "rot": 219.14401245117188
                },
                {
                    "pos": {
                        "x": 40.18145751953125,
                        "y": 23.25391960144043,
                        "z": 157.71026611328126
                    },
                    "rot": 257.6524353027344
                }
            ]
        },
        {
            "id": 141018,
            "pos": [
                {
                    "pos": {
                        "x": 37.918212890625,
                        "y": 23.25391960144043,
                        "z": 139.2071990966797
                    },
                    "rot": 180.0
                }
            ]
        }
    ],
    "paths": [],
    "areas": []
}